steps_track/__init__.py
steps_track/chart.py
steps_track/decorator.py
steps_track/extension/__init__.py
steps_track/extension/llm_track.py
steps_track/pipeline.py
steps_track/pipeline_types.py
steps_track/step.py
steps_track/transport/__init__.py
steps_track/transport/base_transport.py
steps_track/transport/http_transport.py
steps_track-1.12.7.dist-info/METADATA
steps_track-1.12.7.dist-info/WHEEL
steps_track-1.12.7.dist-info/RECORD
