Metadata-Version: 2.3
Name: steps-track
Version: 1.12.7
Summary: An observability tool built to track, inspect and visualize intermediate steps in a pipeline, allowing user to easily debug or analyze through a dashboard.
License: MIT
Keywords: steps-track,steps,track,pipeline,observability,monitoring,rag,llm,visualization,tracing,tracking,debugging,analytics,performance,metrics
Author: lokwkin
Author-email: lokwkin@gmail.com
Requires-Python: >=3.12,<4.0
Classifier: License :: OSI Approved :: MIT License
Classifier: Programming Language :: Python :: 3
Classifier: Programming Language :: Python :: 3.12
Classifier: Programming Language :: Python :: 3.13
Requires-Dist: aiohttp (>=3.11.16,<4.0.0)
Requires-Dist: pydantic (>=2.11.3,<3.0.0)
Requires-Dist: pyee (>=13.0.0,<14.0.0)
Requires-Dist: requests (>=2.32.3,<3.0.0)
Project-URL: Homepage, https://github.com/lokwkin/steps-track
Project-URL: Repository, https://github.com/lokwkin/steps-track
